pinterest/Pinterest.py
pinterest/Registry.py
pinterest/__init__.py
pinterest/exceptions.py
pinterest/utils.py
pinterest_client-1.0.2.dist-info/DESCRIPTION.rst
pinterest_client-1.0.2.dist-info/METADATA
pinterest_client-1.0.2.dist-info/RECORD
pinterest_client-1.0.2.dist-info/WHEEL
pinterest_client-1.0.2.dist-info/metadata.json
pinterest_client-1.0.2.dist-info/top_level.txt
pinterest_client-1.0.2.dist-info/zip-safe
