Metadata-Version: 2.0
Name: pinterest-client
Version: 1.0.2
Summary: A simple python client for Pinterest that support user interact with Pinterest such as simple browser.
Home-page: https://github.com/cvhau/pinterest-client
Author: Hau Van
Author-email: cvhau.tt@gmail.com
License: MIT
Keywords: Python Pinterest Client,Python Pinterest API
Platform: UNKNOWN
Classifier: Development Status :: 5 - Production/Stable
Classifier: Intended Audience :: Developers
Classifier: License :: OSI Approved :: MIT License
Classifier: Programming Language :: Python :: 2.7
Requires-Dist: requests
Requires-Dist: requests-toolbelt
